{
    "Postal (Europe) (Postal Manual)": {
        "languages": "En"
    },
    "3DO Content Library, The (USA) (Disc 16) (Music & Sound Effects)": {
        "languages": "En"
    },
    "Giants - Citizen Kabuto (USA) (Disc 2)": {
        "languages": ""
    },
    "Wacky Races (Japan)": {
        "languages": "Ja"
    },
    "Dungeon Master II - The Legend of Skullkeep (USA)": {
        "languages": "En"
    },
    "3DO Content Library, The (USA) (Disc 15) (Music & Sound Effects)": {
        "languages": "En"
    },
    "3DO Content Library, The (USA) (Disc 9) (Music & Sound Effects)": {
        "languages": "En"
    },
    "Al Unser Jr. Arcade Racing (USA)": {
        "languages": ""
    },
    "A-10 Cuba! (USA)": {
        "languages": ""
    },
    "Rayman 3 - Hoodlum Havoc (USA) (En,Fr,De,Es,It)": {
        "languages": "En, Fr, De, It, Es"
    },
    "Crystal Caliburn (USA)": {
        "languages": ""
    },
    "Quake (USA)": {
        "languages": "En"
    },
    "Total Annihilation (USA) (Disc 2) (Game Disc)": {
        "languages": "En"
    },
    "Phantasmagoria (Europe) (Disc 3)": {
        "languages": "En"
    },
    "LEGO Star Wars - The Video Game (USA)": {
        "languages": ""
    },
    "3DO Content Library, The (USA) (Disc 18) (Music & Sound Effects)": {
        "languages": "En"
    },
    "Rune (Japan)": {
        "languages": ""
    },
    "Sims 2, The - Open for Business (Expansion Pack) (Europe)": {
        "languages": ""
    },
    "Sims 2, The - Seasons (Expansion Pack) (USA)": {
        "languages": "En"
    },
    "Alone in the Dark (France)": {
        "languages": "Fr"
    },
    "3DO Content Library, The (USA) (Disc 38) (Music & Sound Effects)": {
        "languages": "En"
    },
    "Star Wars - Rebel Assault (USA)": {
        "languages": ""
    },
    "Daedalus Encounter, The (UK) (Disc 1)": {
        "languages": "En"
    },
    "Dungeon Master II - The Legend of Skullkeep - The First Chapter (USA)": {
        "languages": "En"
    },
    "3DO Content Library, The (USA) (Disc 21) (Music & Sound Effects)": {
        "languages": "En"
    },
    "Sinkha (USA)": {
        "languages": ""
    },
    "MacAddict - The Disc 84 - August 2003 (USA)": {
        "languages": "En"
    },
    "Theme Park (Japan)": {
        "languages": ""
    },
    "Star Wars - Jedi Knight - Jedi Academy (USA) (Disc 1)": {
        "languages": "En"
    },
    "3DO Content Library, The (USA) (Disc 44) (Music & Sound Effects)": {
        "languages": "En"
    },
    "Phantasmagoria (Europe) (Disc 7)": {
        "languages": "En"
    },
    "Racing Days R (Europe) (En,Fr,De)": {
        "languages": "En, Fr, De"
    },
    "Star Trek - Starfleet Academy (USA) (Disc 1)": {
        "languages": ""
    },
    "Leisure Suit Larry 6 - Shape Up or Slip Out! (USA)": {
        "languages": "En"
    },
    "Carmageddon II - Carpocalypse Now (Europe)": {
        "languages": "En"
    },
    "MacAddict - The Disc 79 - March 2003 (USA)": {
        "languages": "En"
    },
    "SimTown - The Town You Build Yourself! (Japan)": {
        "languages": ""
    },
    "Medal of Honor - Allied Assault (USA) (Disc 2)": {
        "languages": "En"
    },
    "Unreal Tournament 2004 (USA)": {
        "languages": "En"
    },
    "Rise of Nations - Gold Edition (USA)": {
        "languages": "En"
    },
    "Medal of Honor - Allied Assault - Breakthrough (USA)": {
        "languages": "En"
    },
    "Star Wars - Mac Pack (USA)": {
        "languages": ""
    },
    "SimCity 2000 - CD Collection (USA)": {
        "languages": "En"
    },
    "7th Guest, The (USA) (Disc 1)": {
        "languages": "En"
    },
    "Sims, The (USA)": {
        "languages": "En"
    },
    "11th Hour, The (USA) (Disc 3)": {
        "languages": "En"
    },
    "Tomb Raider - The Last Revelation (USA)": {
        "languages": "En"
    },
    "Lara Croft Tomb Raider - Anniversary (USA)": {
        "languages": ""
    },
    "Learn to Play Chess with Fritz & Chesster 2 - Chess in the Black Castle (USA)": {
        "languages": "En"
    },
    "Call of Duty 4 - Modern Warfare (USA)": {
        "languages": "En"
    },
    "3DO Content Library, The (USA) (Disc 46) (Music & Sound Effects)": {
        "languages": "En"
    },
    "Star Wars - Rebel Assault (USA) (Rerelease)": {
        "languages": ""
    },
    "Medal of Honor - Allied Assault (USA) (Disc 1)": {
        "languages": "En"
    },
    "Night Trap (USA) (Disc 1)": {
        "languages": "En"
    },
    "Command & Conquer (USA) (Disc 1)": {
        "languages": "En"
    },
    "Crescent Satsujin Jiken - Hyena no Jijou (Japan)": {
        "languages": "Ja"
    },
    "XXX Vol. 1 (Japan)": {
        "languages": "Ja"
    },
    "3DO Content Library, The (USA) (Disc 12) (Music & Sound Effects)": {
        "languages": "En"
    },
    "Ultra 2000 Series for Mac Vol. 04 - Puyo Puyo for Macintosh (Japan)": {
        "languages": "Ja"
    },
    "MacAddict - The Disc 80 - April 2003 (USA)": {
        "languages": "En"
    },
    "Alex-World (Japan) (Disc 1)": {
        "languages": "Ja"
    },
    "J. B. Harold - Blue Chicago Blues (Japan) (Disc 1)": {
        "languages": "Ja"
    },
    "Rayman 3 - Hoodlum Havoc (USA) (En,Fr,De,Es,It) (Disc 1)": {
        "languages": "En, Fr, De, It, Es"
    },
    "Descent - Lunar Base 1 (USA)": {
        "languages": "En"
    },
    "X2 - Wolverine's Revenge (USA) (Disc 1)": {
        "languages": "En"
    },
    "Star Trek - Elite Force II (USA) (Disc 1)": {
        "languages": ""
    },
    "id Anthology (USA) (Disc 4) (Mac)": {
        "languages": "En"
    },
    "Frankenstein - Through the Eyes of the Monster - The Awakening (USA)": {
        "languages": "En"
    },
    "3DO Content Library, The (USA) (Disc 42) (Music & Sound Effects)": {
        "languages": "En"
    },
    "3DO Content Library, The (USA) (Disc 17) (Music & Sound Effects)": {
        "languages": "En"
    },
    "Full Throttle (Europe)": {
        "languages": ""
    },
    "Obsidian (Japan) (Disc 2)": {
        "languages": ""
    },
    "11th Hour, The (USA) (Disc 2)": {
        "languages": "En"
    },
    "3DO Content Library, The (USA) (Disc 48) (Music & Sound Effects)": {
        "languages": "En"
    },
    "Sid Meier's Civilization IV - Beyond the Sword (USA) (En,Fr,De)": {
        "languages": "En, Fr, De"
    },
    "Railroad Tycoon 3 (USA) (Disc 2) (Play)": {
        "languages": "En"
    },
    "Need for Speed - Carbon (USA)": {
        "languages": ""
    },
    "World Book - 2004 Edition (USA)": {
        "languages": "En"
    },
    "Star Wars - Rebel Assault (Europe)": {
        "languages": "En"
    },
    "Daisenryaku V DX (Japan)": {
        "languages": ""
    },
    "Call of Duty 2 (Europe)": {
        "languages": "En"
    },
    "Links Pro CD (USA)": {
        "languages": "En"
    },
    "Myst (Japan)": {
        "languages": ""
    },
    "Karma - Curse of the 12 Caves (France) (Covermount)": {
        "languages": ""
    },
    "3DO Content Library, The (USA) (Disc 1) (Music & Sound Effects)": {
        "languages": "En"
    },
    "Links Championship Edition (USA) (Disc 4)": {
        "languages": "En"
    },
    "3DO Content Library, The (USA) (Disc 20) (Music & Sound Effects)": {
        "languages": "En"
    },
    "Lost Eden (France)": {
        "languages": "Fr"
    },
    "Daedalus Encounter, The - Episode 1 - Nanpasen no Alien (Japan) (Disc 2)": {
        "languages": ""
    },
    "Total Annihilation (USA) (Disc 1) (Install Disc)": {
        "languages": "En"
    },
    "Duke Nukem 3D - Atomic Edition (Europe)": {
        "languages": "En"
    },
    "Kidou Senshi Gundam Illustration World Vol. 1 (Japan)": {
        "languages": "Ja"
    },
    "Jazz Jackrabbit 2 (USA)": {
        "languages": "En"
    },
    "Meshitsukai 2 (Japan)": {
        "languages": "Ja"
    },
    "Monty Python Sacre Graal (France)": {
        "languages": "Fr"
    },
    "3DO Content Library, The (USA) (Disc 32) (Music & Sound Effects)": {
        "languages": "En"
    },
    "Nick Jr. Dora the Explorer - Animal Adventures (USA)": {
        "languages": ""
    },
    "Eastern Mind - The Lost Souls of Tong Nou (USA)": {
        "languages": "En"
    },
    "Pathways into Darkness (USA)": {
        "languages": "En"
    },
    "Star Trek - Elite Force II (USA) (Disc 2)": {
        "languages": ""
    },
    "3DO Content Library, The (USA) (Disc 40) (Music & Sound Effects)": {
        "languages": "En"
    },
    "Klik & Play (France)": {
        "languages": "Fr"
    },
    "Battlefield 1942 - Secret Weapons of WWII (Expansion Pack) (USA)": {
        "languages": "En"
    },
    "Deus Ex (USA)": {
        "languages": "En"
    },
    "3DO Content Library, The (USA) (Disc 2) (Music & Sound Effects)": {
        "languages": "En"
    },
    "Theme Park (Europe) (En,Fr,De,Es,It)": {
        "languages": "En, Fr, De, It, Es"
    },
    "Star Trek - The Next Generation - Klingon Honor Guard (USA) (Game Disk)": {
        "languages": ""
    },
    "Halo - Combat Evolved (USA)": {
        "languages": "En"
    },
    "Star Wars - The Force Unleashed - Ultimate Sith Edition (USA) (Disc 2)": {
        "languages": ""
    },
    "Doom II (USA, Europe)": {
        "languages": "En"
    },
    "Star Trek - The Next Generation - Klingon Honor Guard (USA) (Install Disk)": {
        "languages": ""
    },
    "Klik & Play (Japan)": {
        "languages": "Ja"
    },
    "Alone in the Dark 3 (France) (Covermount)": {
        "languages": "Fr"
    },
    "Star Wars - Empire at War (USA)": {
        "languages": ""
    },
    "Phantasmagoria (Europe) (Disc 1)": {
        "languages": "En"
    },
    "3DO Content Library, The (USA) (Disc 7) (Music & Sound Effects)": {
        "languages": "En"
    },
    "Medal of Honor - Allied Assault - Spearhead (USA)": {
        "languages": "En"
    },
    "Youkai Ningen Bem - Aratanaru Tamashii no Meikyuu (Japan) (Disc 1) (Game)": {
        "languages": "Ja"
    },
    "Secret du Templier, Le (France) (Covermount)": {
        "languages": "Fr"
    },
    "3-D Ultra Pinball - Creep Night (France)": {
        "languages": "Fr"
    },
    "Unreal Tournament (USA)": {
        "languages": "En"
    },
    "MacAddict - The Disc 81 - May 2003 (USA)": {
        "languages": "En"
    },
    "3DO Content Library, The (USA) (Disc 50) (Music & Sound Effects)": {
        "languages": "En"
    },
    "Atlantis - Das sagenhafte Abenteuer (Germany) (Disc 1)": {
        "languages": "De"
    },
    "Unreal (USA)": {
        "languages": "En"
    },
    "3DO Content Library, The (USA) (Disc 49) (Music & Sound Effects)": {
        "languages": "En"
    },
    "Putt-Putt's Fun Pack (USA)": {
        "languages": "En"
    },
    "Daedalus Encounter, The - Episode 1 - Nanpasen no Alien (Japan) (Disc 1)": {
        "languages": ""
    },
    "Bandai Visual CD-ROM Previews for Macintosh Vol. 2 (Japan)": {
        "languages": "Ja"
    },
    "Dark Corona Pegasus (Europe)": {
        "languages": "En"
    },
    "3DO Content Library, The (USA) (Disc 6) (Music & Sound Effects)": {
        "languages": "En"
    },
    "Descent (USA)": {
        "languages": "En"
    },
    "Star Wars - Rebel Assault (USA) (v1.01)": {
        "languages": ""
    },
    "Phantasmagoria (Europe) (Disc 4)": {
        "languages": "En"
    },
    "MDK (Europe)": {
        "languages": "En"
    },
    "Centipede (USA)": {
        "languages": "En"
    },
    "Quake III - Arena (Europe)": {
        "languages": "En"
    },
    "3DO Content Library, The (USA) (Disc 28) (Music & Sound Effects)": {
        "languages": "En"
    },
    "Residents, The - Gingerbread Man (Europe) (Expanded Album)": {
        "languages": "En"
    },
    "Indiana Jones and the Fate of Atlantis (USA) (Rerelease)": {
        "languages": ""
    },
    "Prisoner of Ice (France) (En,Fr,De,Nl,Sv) (Covermount)": {
        "languages": "Nl, En, Fr, De, Sv"
    },
    "Links Championship Edition (USA) (Disc 1)": {
        "languages": "En"
    },
    "3DO Content Library, The (USA) (Disc 31) (Music & Sound Effects)": {
        "languages": "En"
    },
    "Mario Teaches Typing (USA)": {
        "languages": "En"
    },
    "Yoot Tower (USA)": {
        "languages": "En"
    },
    "3DO Content Library, The (USA) (Disc 37) (Music & Sound Effects)": {
        "languages": "En"
    },
    "Ginga Eiyuu Densetsu V (Japan)": {
        "languages": ""
    },
    "3DO Content Library, The (USA) (Disc 47) (Music & Sound Effects)": {
        "languages": "En"
    },
    "Berlin im Untergrund - Eine Interaktive Zeitreise unter den Potsdamer Platz (Germany)": {
        "languages": "De"
    },
    "Star Wars - Rebel Assault II - The Hidden Empire (USA) (Disc 1)": {
        "languages": ""
    },
    "Total Annihilation - The Core Contingency & Total Annihilation - Battle Tactics (USA)": {
        "languages": "En"
    },
    "Myst (USA) (Rerelease)": {
        "languages": "En"
    },
    "Phantasmagoria (Europe) (Disc 5)": {
        "languages": "En"
    },
    "Links LS 2000 (USA) (Disc 1)": {
        "languages": "En"
    },
    "Tomb Raider - The Last Revelation (Europe)": {
        "languages": "En"
    },
    "Guignols de l'Info, Les... le Jeu! (France)": {
        "languages": "Fr"
    },
    "Lara Croft Tomb Raider - The Angel of Darkness (USA) (Disc 2)": {
        "languages": ""
    },
    "Tomb Raider II - Starring Lara Croft (Canada)": {
        "languages": ""
    },
    "Night Trap (USA) (Disc 2)": {
        "languages": "En"
    },
    "Zork Nemesis - The Forbidden Lands (France) (Disc 2)": {
        "languages": "En"
    },
    "Giants - Citizen Kabuto (USA) (Disc 1)": {
        "languages": ""
    },
    "Fly! (Europe) (Disc 1)": {
        "languages": "En"
    },
    "Atlantis - Das sagenhafte Abenteuer (Germany) (Disc 4)": {
        "languages": "De"
    },
    "3DO Content Library, The (USA) (Disc 43) (Music & Sound Effects)": {
        "languages": "En"
    },
    "Dig, The (UK)": {
        "languages": "En"
    },
    "Alone in the Dark 2 (France) (Covermount)": {
        "languages": "Fr"
    },
    "Chu-Teng (Japan)": {
        "languages": "Ja"
    },
    "3DO Content Library, The (USA) (Disc 45) (Music & Sound Effects)": {
        "languages": "En"
    },
    "Star Wars - X-Wing - Collector's CD-ROM (USA)": {
        "languages": ""
    },
    "Puyo Puyo Fever (Japan)": {
        "languages": "Ja"
    },
    "Age of Empires II - Gold Edition (USA)": {
        "languages": "En"
    },
    "Tomb Raider - Underworld (USA)": {
        "languages": ""
    },
    "Mario Teaches Typing (USA) (Rev 1)": {
        "languages": "En"
    },
    "Links LS 2000 (USA) (Disc 2)": {
        "languages": "En"
    },
    "Rayman 3 - Hoodlum Havoc (USA, Europe) (En,Fr,De,Es,It) (Disc 2)": {
        "languages": "En, Fr, De, It, Es"
    },
    "Links Championship Edition (USA) (Disc 2)": {
        "languages": "En"
    },
    "Unreal Tournament (Europe)": {
        "languages": "En"
    },
    "Star Wars - Knights of the Old Republic (USA)": {
        "languages": ""
    },
    "3DO Content Library, The (USA) (Disc 30) (Music & Sound Effects)": {
        "languages": "En"
    },
    "Sid Meier's Civilization II (USA)": {
        "languages": "En"
    },
    "Abuse for Macintosh (USA)": {
        "languages": "En"
    },
    "SimPeople (Japan) (Rerelease)": {
        "languages": ""
    },
    "LEGO Star Wars II - The Original Trilogy (USA, Europe)": {
        "languages": ""
    },
    "Monty Python's Complete Waste of Time (USA)": {
        "languages": "En"
    },
    "Daedalus Encounter, The (UK) (Disc 2)": {
        "languages": "En"
    },
    "Fly! (Europe) (Disc 3)": {
        "languages": "En"
    },
    "Virtual Variety Show (Japan)": {
        "languages": "Ja"
    },
    "Caesar II (Europe)": {
        "languages": "En"
    },
    "MacAddict - The Disc 85 - September 2003 (USA)": {
        "languages": "En"
    },
    "Marathon (USA) (Rerelease)": {
        "languages": "En"
    },
    "3DO Content Library, The (USA) (Disc 8) (Music & Sound Effects)": {
        "languages": "En"
    },
    "Youkai Ningen Bem - Aratanaru Tamashii no Meikyuu (Japan) (Disc 2) (Data Base)": {
        "languages": "Ja"
    },
    "Ultimate Doom, The (USA)": {
        "languages": "En"
    },
    "Phantasmagoria (Europe) (Disc 2)": {
        "languages": "En"
    },
    "3DO Content Library, The (USA) (Disc 41) (Music & Sound Effects)": {
        "languages": "En"
    },
    "Sims, The - Vacation (Expansion Pack) (USA)": {
        "languages": "En"
    },
    "Star Fighter (USA)": {
        "languages": "En"
    },
    "Star Wars - Dark Forces (USA) (Special Edition - 3 Playable Levels)": {
        "languages": "En"
    },
    "Myst (Europe) (Rerelease)": {
        "languages": "En"
    },
    "Bandai Visual CD-ROM Previews for Macintosh Vol. 3 (Japan)": {
        "languages": ""
    },
    "StarCraft - Brood War (Expansion Set) (Europe)": {
        "languages": "En"
    },
    "Aquazone Compact (Japan)": {
        "languages": ""
    },
    "3DO Content Library, The (USA) (Disc 26) (Music & Sound Effects)": {
        "languages": "En"
    },
    "Worms 3D (USA)": {
        "languages": ""
    },
    "Atlantis - Das sagenhafte Abenteuer (Germany) (Disc 3)": {
        "languages": "De"
    },
    "Star Wars - Episode I - Racer (Germany) (En,De)": {
        "languages": "En, De"
    },
    "Oceans Below (Japan)": {
        "languages": ""
    },
    "Zork Nemesis - The Forbidden Lands (France) (Disc 3)": {
        "languages": "En"
    },
    "Tomb Raider II - Starring Lara Croft (USA)": {
        "languages": "En"
    },
    "11th Hour, The (USA) (Disc 4)": {
        "languages": "En"
    },
    "Links LS (USA) (Disc 1)": {
        "languages": "En"
    },
    "Obsidian (Japan) (Disc 4)": {
        "languages": ""
    },
    "Obsidian (Japan) (Disc 1)": {
        "languages": ""
    },
    "Crescent Satsujin Jiken - Reporter Saotome Kyouko (Japan)": {
        "languages": "Ja"
    },
    "Terry Pratchett's Discworld (UK)": {
        "languages": "En"
    },
    "3DO Content Library, The (USA) (Disc 22) (Music & Sound Effects)": {
        "languages": "En"
    },
    "Indiana Jones and the Fate of Atlantis (USA)": {
        "languages": "En"
    },
    "Rayman 3 - Hoodlum Havoc (Europe) (En,Fr,De,Es,It) (Disc 1)": {
        "languages": "En, Fr, De, It, Es"
    },
    "SimCity 2000 Special Edition (USA)": {
        "languages": "En"
    },
    "Gadget - Invention, Travel, & Adventure (Japan)": {
        "languages": ""
    },
    "3DO Content Library, The (USA) (Disc 10) (Music & Sound Effects)": {
        "languages": "En"
    },
    "MacAttack (Europe)": {
        "languages": "En"
    },
    "Zork Nemesis (Japan) (Disc I)": {
        "languages": ""
    },
    "3DO Content Library, The (USA) (Disc 11) (Music & Sound Effects)": {
        "languages": "En"
    },
    "Rayman 3 - Hoodlum Havoc (USA) (En,Fr,De,Es,It) (Disc 3)": {
        "languages": "En, Fr, De, It, Es"
    },
    "Daedalus Encounter, The - Episode 1 - Nanpasen no Alien (Japan) (Disc 3)": {
        "languages": ""
    },
    "Star Wars - Dark Forces (Europe)": {
        "languages": "En"
    },
    "Myst (USA)": {
        "languages": "En"
    },
    "Residents, The - Freak Show (USA)": {
        "languages": "En"
    },
    "MacWorld - 20th Anniversary - February 2004 (USA)": {
        "languages": "En"
    },
    "Transmigration (Japan) (Disc 2) (Transcript)": {
        "languages": "Ja"
    },
    "Shadow Warrior (USA, Europe)": {
        "languages": "En"
    },
    "Crescent Satsujin Jiken - Tozasareta Nikki (Japan)": {
        "languages": "Ja"
    },
    "Freedom Force (USA)": {
        "languages": "En"
    },
    "StarCraft (Europe)": {
        "languages": "En"
    },
    "Atlantis - Das sagenhafte Abenteuer (Germany) (Disc 2)": {
        "languages": "De"
    },
    "Call of Duty 4 - Modern Warfare (Europe)": {
        "languages": "En"
    },
    "Tong-Nou (Japan)": {
        "languages": "Ja"
    },
    "Aquazone Deluxe (Japan)": {
        "languages": ""
    },
    "BrainDead 13 (USA)": {
        "languages": "En"
    },
    "Star Wars - Jedi Knight II - Jedi Outcast (USA)": {
        "languages": ""
    },
    "Lara Croft Tomb Raider - The Angel of Darkness (USA) (Disc 1)": {
        "languages": ""
    },
    "Star Wars - The Force Unleashed - Ultimate Sith Edition (USA) (Disc 1)": {
        "languages": ""
    },
    "Ishido - The Way of Stones (USA)": {
        "languages": "En"
    },
    "3DO Content Library, The (USA) (Disc 29) (Music & Sound Effects)": {
        "languages": "En"
    },
    "3DO Content Library, The (USA) (Disc 33) (Music & Sound Effects)": {
        "languages": "En"
    },
    "Shanghai - Double Pack (USA)": {
        "languages": ""
    },
    "Tony Hawk's Pro Skater 2 (USA)": {
        "languages": "En"
    },
    "Tomb Raider Chronicles (USA) (Game Disc)": {
        "languages": ""
    },
    "Obsidian (Japan) (Disc 3)": {
        "languages": ""
    },
    "Star Trek - Voyager - Elite Force (USA)": {
        "languages": "En"
    },
    "3DO Content Library, The (USA) (Disc 3) (Music & Sound Effects)": {
        "languages": "En"
    },
    "3DO Content Library, The (USA) (Disc 39) (Music & Sound Effects)": {
        "languages": "En"
    },
    "Zork Nemesis (Japan) (Disc II)": {
        "languages": ""
    },
    "Star Wars - Rebel Assault II - The Hidden Empire (USA) (Disc 2)": {
        "languages": ""
    },
    "Lords of the Realm II + Siege Pack (USA)": {
        "languages": "En"
    },
    "Fly! 2K (USA) (Disc 3) (Sectional Charts)": {
        "languages": "En"
    },
    "Sid Meier's Civilization III Complete (USA)": {
        "languages": "En"
    },
    "Virtual Pool 3D (USA)": {
        "languages": "En"
    },
    "Quake (Europe)": {
        "languages": "En"
    },
    "Obsidian (Japan) (Disc 5)": {
        "languages": ""
    },
    "Star Wars - Dark Forces (USA)": {
        "languages": ""
    },
    "Railroad Tycoon 3 (USA) (Disc 1) (Install)": {
        "languages": "En"
    },
    "Tomb Raider III - Adventures of Lara Croft (USA)": {
        "languages": "En"
    },
    "Cookie's Bustle - Mysterious Bombo World (Japan)": {
        "languages": "Ja"
    },
    "Command & Conquer (USA) (Disc 2)": {
        "languages": "En"
    },
    "3DO Content Library, The (USA) (Disc 13) (Music & Sound Effects)": {
        "languages": "En"
    },
    "Maniac Mansion - Day of the Tentacle (France)": {
        "languages": "Fr"
    },
    "Frankenstein - Through the Eyes of the Monster (USA)": {
        "languages": "En"
    },
    "Myst - Masterpiece Edition (Germany) (Rerelease)": {
        "languages": "De"
    },
    "3DO Content Library, The (USA) (Disc 19) (Music & Sound Effects)": {
        "languages": "En"
    },
    "Marathon 2 - Durandal (USA)": {
        "languages": ""
    },
    "3DO Content Library, The (USA) (Disc 35) (Music & Sound Effects)": {
        "languages": "En"
    },
    "3-D Ultra Pinball (Europe)": {
        "languages": "En"
    },
    "SimCity 2000 - CD Collection (Europe)": {
        "languages": "En"
    },
    "Links Championship Edition (USA) (Disc 3)": {
        "languages": "En"
    },
    "Afterlife (France)": {
        "languages": "En"
    },
    "3DO Content Library, The (USA) (Disc 27) (Music & Sound Effects)": {
        "languages": "En"
    },
    "Monopoly Casino (USA)": {
        "languages": "En"
    },
    "Ukiuki Tsuri Tengoku 2 - Hato no Gomokuzuri (Japan)": {
        "languages": ""
    },
    "Settlers II, The - Veni, Vidi, Vici (USA)": {
        "languages": "En"
    },
    "Age of Empires (USA)": {
        "languages": "En"
    },
    "Links LS (USA, Europe) (Disc 3)": {
        "languages": "En"
    },
    "X2 - Wolverine's Revenge (USA) (Disc 2)": {
        "languages": "En"
    },
    "11th Hour, The (USA) (Disc 1)": {
        "languages": "En"
    },
    "Star Wars - Jedi Knight - Jedi Academy (USA) (Disc 2)": {
        "languages": "En"
    },
    "SiN Gold (USA)": {
        "languages": "En"
    },
    "Busy World of Richard Scarry, The - Busytown (USA)": {
        "languages": "En"
    },
    "3DO Content Library, The (USA) (Disc 36) (Music & Sound Effects)": {
        "languages": "En"
    },
    "Stubbs the Zombie in Rebel Without a Pulse (USA) (En,Fr)": {
        "languages": "En, Fr"
    },
    "Fly! (Europe) (Disc 2)": {
        "languages": "En"
    },
    "Kid Pix Deluxe 3X (USA)": {
        "languages": "En"
    },
    "Rayman 3 - Hoodlum Havoc (Europe) (En,Fr,De,Es,It) (Disc 3)": {
        "languages": "En, Fr, De, It, Es"
    },
    "Aquazone Compact (Japan) (Rerelease)": {
        "languages": ""
    },
    "3DO Content Library, The (USA) (Disc 24) (Music & Sound Effects)": {
        "languages": "En"
    },
    "Age of Empires (USA) (v1.0b)": {
        "languages": "En"
    },
    "Harry Potter and the Sorcerer's Stone (USA)": {
        "languages": "En"
    },
    "Doom 3 (USA)": {
        "languages": "En"
    },
    "Zork Nemesis (Japan) (Disc III)": {
        "languages": ""
    },
    "3DO Content Library, The (USA) (Disc 34) (Music & Sound Effects)": {
        "languages": "En"
    },
    "Links LS 2000 (USA) (Disc 3)": {
        "languages": "En"
    },
    "Return to Zork (Europe)": {
        "languages": "En"
    },
    "Prince of Persia (USA)": {
        "languages": ""
    },
    "3DO Content Library, The (USA) (Disc 5) (Music & Sound Effects)": {
        "languages": "En"
    },
    "Mad Dog McCree (USA)": {
        "languages": "En"
    },
    "Alex-World (Japan) (Disc 2)": {
        "languages": "Ja"
    },
    "Sotsugyou - Graduation (Japan)": {
        "languages": "Ja"
    },
    "Tomb Raider Chronicles (USA) (Level Editor Disc)": {
        "languages": ""
    },
    "International Tennis Open (Europe) (En,Fr)": {
        "languages": "En, Fr"
    },
    "Bandai Visual CD-ROM Previews for Macintosh Vol. 1 (Japan)": {
        "languages": "Ja"
    },
    "Star Wars - TIE Fighter - Collector's CD-ROM (USA)": {
        "languages": ""
    },
    "Metal Gear Solid (Australia) (Artwork Vol. 2)": {
        "languages": "En"
    },
    "Zork Nemesis - The Forbidden Lands (France) (Disc 1)": {
        "languages": "En"
    },
    "Space Quest 6 - Roger Wilco in the Spinal Frontier (France)": {
        "languages": "En"
    },
    "Bungie Mac Action Sack (USA)": {
        "languages": "En"
    },
    "Virtual Pool (USA)": {
        "languages": "En"
    },
    "Eberouge (Japan)": {
        "languages": ""
    },
    "3DO Content Library, The (USA) (Disc 4) (Music & Sound Effects)": {
        "languages": "En"
    },
    "Jack Nicklaus 4 (USA)": {
        "languages": ""
    },
    "Metal Gear Solid (Australia) (Artwork Vol. 1)": {
        "languages": "En"
    },
    "Call of Duty (Europe) (Deluxe Edition)": {
        "languages": "En"
    },
    "3DO Content Library, The (USA) (Disc 25) (Music & Sound Effects)": {
        "languages": "En"
    },
    "Links LS (USA) (Disc 2)": {
        "languages": "En"
    },
    "Fly! 2K (USA) (Disc 2) (Satellite Scenery)": {
        "languages": "En"
    },
    "Darkseed (Europe) (Fr,De)": {
        "languages": "Fr, De"
    },
    "Driver - You Are the Wheelman (USA)": {
        "languages": "En"
    },
    "Phantasmagoria (Europe) (Disc 6)": {
        "languages": "En"
    },
    "3DO Content Library, The (USA) (Disc 23) (Music & Sound Effects)": {
        "languages": "En"
    },
    "WipEout 2097 (Europe)": {
        "languages": "En"
    },
    "Legend of Kyrandia, The (USA)": {
        "languages": "En"
    },
    "Fly! 2K (USA) (Disc 1) (Program Install)": {
        "languages": "En"
    },
    "3DO Content Library, The (USA) (Disc 14) (Music & Sound Effects)": {
        "languages": "En"
    },
    "SimTown - The Town You Build Yourself! (USA)": {
        "languages": ""
    },
    "Saikyou Kareshi - Dynamic Darling (Japan)": {
        "languages": "Ja"
    },
    "Lunicus (Japan)": {
        "languages": "Ja"
    },
    "Star Wars - Battlefront (USA)": {
        "languages": ""
    },
    "Tomb Raider Gold (USA)": {
        "languages": "En"
    },
    "Activision's Atari 2600 Action Pack for Macintosh (USA)": {
        "languages": ""
    },
    "Reader Rabbit - 1st Grade (USA) (Rerelease)": {
        "languages": ""
    },
    "Railroad Tycoon II (USA)": {
        "languages": "En"
    },
    "Alone in the Dark (France) (Covermount)": {
        "languages": ""
    },
    "Star Wars - Jedi Knight Gold Pack (USA)": {
        "languages": ""
    },
    "Myst (Germany) (Rerelease)": {
        "languages": "De"
    },
    "Mario Is Missing! CD-ROM Deluxe (USA)": {
        "languages": "En"
    },
    "CD-ROM MacLife No. 11 (Japan)": {
        "languages": ""
    },
    "CD-ROM MacLife No. 13 (Japan)": {
        "languages": ""
    },
    "CD-ROM MacLife No. 132 (Japan)": {
        "languages": ""
    },
    "CD-ROM MacLife No. 147 (Japan)": {
        "languages": ""
    },
    "CD-ROM MacLife No. 28 (Japan)": {
        "languages": ""
    },
    "CD-ROM MacLife No. 29 (Japan)": {
        "languages": ""
    },
    "CD-ROM MacLife No. 30 (Japan)": {
        "languages": ""
    },
    "CD-ROM MacLife No. 34 (Japan)": {
        "languages": ""
    },
    "CD-ROM MacLife No. 45 (Japan)": {
        "languages": ""
    },
    "CD-ROM MacLife No. 46 (Japan)": {
        "languages": ""
    },
    "CD-ROM MacLife No. 27 (Japan)": {
        "languages": ""
    },
    "Legend of Kyrandia, The - Book Three (USA)": {
        "languages": "En"
    },
    "Quake II (USA)": {
        "languages": "En"
    },
    "CD-ROM MacLife No. 129 (Japan)": {
        "languages": ""
    },
    "CD-ROM MacLife No. 128 (Japan)": {
        "languages": ""
    },
    "Elemental Force (Japan)": {
        "languages": "Ja"
    },
    "Green Eggs and Ham (USA)": {
        "languages": "En"
    },
    "Cat in the Hat, The (USA)": {
        "languages": "En"
    },
    "Arcade Battles (USA)": {
        "languages": "En"
    },
    "Ginga Eiyuu Densetsu - Screen Saver Vol. 2 for Macintosh (Japan)": {
        "languages": ""
    },
    "Bedlam (USA) (En,Fr,De,Es,It,Nl)": {
        "languages": "Nl, En, Fr, De, It, Es"
    },
    "Enemy Engaged - RAH-66 Comanche Versus KA-52 Hokum (Europe) (En,Fr,De,It)": {
        "languages": "En, Fr, De, It"
    },
    "CD-ROM MacLife No. 1 (Japan)": {
        "languages": ""
    },
    "CD-ROM MacLife No. 5 (Japan)": {
        "languages": ""
    },
    "CD-ROM MacLife No. 6 (Japan)": {
        "languages": ""
    },
    "CD-ROM MacLife No. 7 (Japan)": {
        "languages": ""
    },
    "CD-ROM MacLife No. 8 (Japan)": {
        "languages": ""
    },
    "CD-ROM MacLife No. 9 (Japan)": {
        "languages": ""
    },
    "CD-ROM MacLife No. 10 (Japan)": {
        "languages": ""
    },
    "Gadget - Invention, Travel, & Adventure (USA)": {
        "languages": "En"
    },
    "Mario's Time Machine Deluxe (USA)": {
        "languages": "En"
    },
    "CD-ROM MacLife No. 12 (Japan)": {
        "languages": ""
    },
    "CD-ROM MacLife No. 14 (Japan)": {
        "languages": ""
    },
    "CD-ROM MacLife No. 15 (Japan)": {
        "languages": ""
    },
    "CD-ROM MacLife No. 16 (Japan)": {
        "languages": ""
    },
    "CD-ROM MacLife No. 17 (Japan)": {
        "languages": ""
    },
    "CD-ROM MacLife No. 18 (Japan)": {
        "languages": ""
    },
    "CD-ROM MacLife No. 19 (Japan)": {
        "languages": ""
    },
    "Colin McRae Rally Mac (Europe) (En,Fr,De,Es,It)": {
        "languages": "En, Fr, De, It, Es"
    },
    "CD-ROM MacLife No. 20 (Japan) (Disc 1)": {
        "languages": ""
    },
    "CD-ROM MacLife No. 20 (Japan) (Disc 2)": {
        "languages": ""
    },
    "CD-ROM MacLife No. 21 (Japan)": {
        "languages": ""
    },
    "CD-ROM MacLife No. 22 (Japan)": {
        "languages": ""
    },
    "CD-ROM MacLife No. 23 (Japan)": {
        "languages": ""
    },
    "Gridz (USA)": {
        "languages": "En"
    },
    "SimCity 3000 (USA)": {
        "languages": "En"
    },
    "Sims 2, The (USA) (En,Ja,Fr,De,It)": {
        "languages": "En, Fr, De, It, Ja"
    },
    "SimCity 4 (USA) (En,Ja,Fr,De,Es,It,Nl,Pt,Sv,No,Da,Fi,Zh,Ko,Pl,Th) (Disc 1)": {
        "languages": "Zh, Da, Nl, En, Fi, Fr, De, It, Ja, Ko, No, Pl, Pt, Es, Sv, Th"
    },
    "SimCity 4 (USA) (En,Ja,Fr,De,Es,It,Nl,Pt,Sv,No,Da,Fi,Zh,Ko,Pl,Th) (Disc 2)": {
        "languages": "Zh, Da, Nl, En, Fi, Fr, De, It, Ja, Ko, No, Pl, Pt, Es, Sv, Th"
    },
    "CD-ROM MacLife No. 24 (Japan)": {
        "languages": ""
    },
    "CD-ROM MacLife No. 25 (Japan)": {
        "languages": ""
    },
    "CD-ROM MacLife No. 25 - Special Edition (Japan) (MkLinux Nihongo Kit)": {
        "languages": ""
    },
    "CD-ROM MacLife No. 26 (Japan)": {
        "languages": ""
    },
    "Descent - Levels of the World (USA)": {
        "languages": "En"
    },
    "Train Simulator - Chuuou-sen (201-kei) (Japan)": {
        "languages": "Ja"
    },
    "Train Simulator - Toukaidou Honsen (211-kei) (Japan)": {
        "languages": "Ja"
    },
    "Train Simulator - JR Shikoku Vol. 1 (Takamatsu-Kotohira, Takamatsu-Kojima) (Japan)": {
        "languages": "Ja"
    },
    "CD-ROM MacLife No. 31 (Japan)": {
        "languages": ""
    },
    "CD-ROM MacLife No. 32 (Japan)": {
        "languages": ""
    },
    "CD-ROM MacLife No. 33 (Japan)": {
        "languages": ""
    },
    "CD-ROM MacLife No. 35 (Japan)": {
        "languages": ""
    },
    "CD-ROM MacLife No. 36 (Japan)": {
        "languages": ""
    },
    "CD-ROM MacLife No. 37 (Japan)": {
        "languages": ""
    },
    "CD-ROM MacLife No. 38 (Japan)": {
        "languages": ""
    },
    "CD-ROM MacLife No. 39 (Japan)": {
        "languages": ""
    },
    "CD-ROM MacLife No. 40 (Japan)": {
        "languages": ""
    },
    "Star Wars - X-Wing - Collector's CD-ROM (Japan)": {
        "languages": ""
    },
    "Kid Pix 3D (USA)": {
        "languages": "En"
    },
    "CD-ROM MacLife No. 41 (Japan)": {
        "languages": ""
    },
    "CD-ROM MacLife No. 42 (Japan)": {
        "languages": ""
    },
    "CD-ROM MacLife No. 43 (Japan)": {
        "languages": ""
    },
    "CD-ROM MacLife No. 44 (Japan)": {
        "languages": ""
    },
    "CD-ROM MacLife No. 47 (Japan)": {
        "languages": ""
    },
    "CD-ROM MacLife No. 131 (Japan)": {
        "languages": ""
    },
    "CD-ROM MacLife No. 143 (Japan)": {
        "languages": ""
    },
    "CD-ROM MacLife No. 144 (Japan)": {
        "languages": ""
    },
    "CD-ROM MacLife No. 145 (Japan)": {
        "languages": ""
    },
    "CD-ROM MacLife No. 146 (Japan)": {
        "languages": ""
    },
    "CD-ROM MacLife No. 148 (Japan)": {
        "languages": ""
    },
    "CD-ROM MacLife No. 149 (Japan)": {
        "languages": ""
    },
    "CD-ROM MacLife No. 151 (Japan)": {
        "languages": ""
    },
    "CD-ROM MacLife No. 152 (Japan)": {
        "languages": ""
    },
    "CD-ROM MacLife No. 153 (Japan)": {
        "languages": ""
    },
    "CD-ROM MacLife No. 154 (Japan)": {
        "languages": ""
    },
    "CD-ROM MacLife No. 155 (Japan)": {
        "languages": ""
    },
    "CD-ROM MacLife No. 156 (Japan)": {
        "languages": ""
    },
    "CD-ROM MacLife No. 140 (Japan) (Disc 1)": {
        "languages": ""
    },
    "CD-ROM MacLife No. 150 (Japan)": {
        "languages": ""
    },
    "CD-ROM MacLife No. 157 (Japan)": {
        "languages": ""
    },
    "CD-ROM MacLife No. 158 (Japan)": {
        "languages": ""
    },
    "CD-ROM MacLife No. 159 (Japan)": {
        "languages": ""
    },
    "CD-ROM MacLife No. 160 (Japan)": {
        "languages": ""
    },
    "CD-ROM MacLife No. 161 (Japan)": {
        "languages": ""
    },
    "MacLife 50-gou Kinen Gouka CD-ROM (Japan)": {
        "languages": ""
    },
    "MacPeople 1997 No. 16-No. 17 8.15-9.1 (Japan)": {
        "languages": ""
    },
    "MacPeople 1997 No. 8 4.15 (Japan)": {
        "languages": ""
    },
    "MacPeople 1998 No. 2 1.15 (Japan)": {
        "languages": ""
    }
}
