{
    "3rd Degree (USA)": {
        "languages": "En"
    },
    "7th Guest, The (Europe) (Disc 1) (The Game)": {
        "languages": "En"
    },
    "7th Guest, The (France) (Disc 1) (Le Jeu)": {
        "languages": "Fr"
    },
    "7th Guest, The (Germany) (Disc 1) (Das Spiel)": {
        "languages": "De"
    },
    "7th Guest, The (USA) (Disc 1) (The Game)": {
        "languages": "En"
    },
    "ACT College Search '92, The (USA)": {
        "languages": ""
    },
    "Affaire Morlov, L' (Europe) (En,Fr)": {
        "languages": "En, Fr"
    },
    "Albero Azzurro, L' (Italy)": {
        "languages": "It"
    },
    "Alice au Pays des Merveilles (France)": {
        "languages": "Fr"
    },
    "Alice in Wonderland (Europe)": {
        "languages": "En"
    },
    "Alice in Wonderland (Netherlands)": {
        "languages": "Nl"
    },
    "Alien Gate (Europe)": {
        "languages": "En"
    },
    "Alien Gate (USA)": {
        "languages": "En"
    },
    "Alien Gate (USA) (Rev 1)": {
        "languages": "En"
    },
    "All the Fun of the Fair - Engels voor Kinderen (Netherlands)": {
        "languages": ""
    },
    "Alles over CD-i (Netherlands)": {
        "languages": "Nl"
    },
    "Alles over CD-i (Netherlands) (Apr-Mei 1995)": {
        "languages": "Nl"
    },
    "Amsterdam Auto Rai (Netherlands)": {
        "languages": "Nl"
    },
    "Amsterdamse Effectenbeurs, De (Netherlands)": {
        "languages": ""
    },
    "Ange et le Demon, L' (France)": {
        "languages": "Fr"
    },
    "Anne Willan Presents the Food of France (Europe)": {
        "languages": "En"
    },
    "Anne Willan Presents the Food of France (USA)": {
        "languages": ""
    },
    "Antonio Vega - Oceano del Sol (Spain)": {
        "languages": ""
    },
    "Apprentice, The (Europe)": {
        "languages": "En"
    },
    "Art of Performing, The (Netherlands)": {
        "languages": "Nl"
    },
    "Arte degli Zar, L' - San Pietroburgo e i Tesori dell'Ermitage (Italy)": {
        "languages": "It"
    },
    "Asterix - Caesar's Challenge (Europe)": {
        "languages": ""
    },
    "Asterix - De Uitdaging van Caesar (Netherlands)": {
        "languages": "Nl"
    },
    "Asterix - Die grosse Reise (Germany)": {
        "languages": "De"
    },
    "Asterix - El Desafio de Cesar (Spain)": {
        "languages": "Es"
    },
    "Asterix - La Sfida di Cesare (Italy)": {
        "languages": "It"
    },
    "Asterix - Le Defi de Cesar (France)": {
        "languages": "Fr"
    },
    "Asterix - Le Defi de Cesar (France) (Rev 1)": {
        "languages": "Fr"
    },
    "Atlantis - The Last Resort (Europe)": {
        "languages": "En"
    },
    "Aventures de Sandy au Cirque, Les (France)": {
        "languages": "Fr"
    },
    "Axis and Allies (USA)": {
        "languages": "En"
    },
    "Backgammon (USA, Europe)": {
        "languages": "En"
    },
    "Bande Annonce, La - Automne-Hiver 95-96 (France)": {
        "languages": ""
    },
    "Battleship (USA, Europe)": {
        "languages": "En"
    },
    "Bavaria Film - Eine Interaktive Entdeckungsreise (Germany)": {
        "languages": "De"
    },
    "Beauty Guide (Netherlands)": {
        "languages": "Nl"
    },
    "Beer Is Los!, De (Netherlands)": {
        "languages": "Nl"
    },
    "Bell Atlantic Info-Active Electronic Directory (USA)": {
        "languages": "En"
    },
    "Bell Atlantic InfoTravel - Washington, D.C. (USA)": {
        "languages": "En"
    },
    "Berenstain Bears, The - Bij de Berenstain Beren Thuis - Thuis en bij Jou (Netherlands)": {
        "languages": "Nl"
    },
    "Berenstain Bears, The - On Their Own (USA)": {
        "languages": "En"
    },
    "Bertelsmann Universal Lexikon (Germany) (Fuer CD-i Player mit Digital Video Cartridge)": {
        "languages": "De"
    },
    "Bertelsmann Universal Lexikon (Germany) (Fuer CD-i Player ohne Digital Video Cartridge)": {
        "languages": "De"
    },
    "Black Rain (Germany) (Disc 1)": {
        "languages": "De"
    },
    "Black Rain (Germany) (Disc 2)": {
        "languages": "De"
    },
    "Bradley Fighting Vehicle - Operation Desert Storm - Sustainment Training (USA)": {
        "languages": "En"
    },
    "BrainDead 13 (Europe)": {
        "languages": "En"
    },
    "Breast Self-Examination - Auto-Examen Del Seno (USA) (En,Es)": {
        "languages": "En, Es"
    },
    "Brer Rabbit and the Wonderful Tar Baby (Europe)": {
        "languages": "En"
    },
    "Bryan Adams - Waking Up the Neighbours (Europe)": {
        "languages": ""
    },
    "Burn-Cycle (France) (Demo)": {
        "languages": ""
    },
    "Burn-Cycle (France) (Jeu)": {
        "languages": "Fr"
    },
    "Burn-Cycle (Germany) (Das Spiel)": {
        "languages": "De"
    },
    "Burn-Cycle (Italy) (Il Gioco)": {
        "languages": "It"
    },
    "Burn-Cycle (Spain)": {
        "languages": "Es"
    },
    "Burn-Cycle (USA)": {
        "languages": ""
    },
    "Burn-Cycle (USA, Europe) (Disc 1) (The Game)": {
        "languages": "En"
    },
    "CD Shoot (Europe) (En,Ja,Fr,De,Es,It,Nl,Pt)": {
        "languages": "Nl, En, Fr, De, It, Ja, Pt, Es"
    },
    "CD Shoot (USA)": {
        "languages": ""
    },
    "CD-I Music Book - Classical Guitar Volume 1 (USA)": {
        "languages": ""
    },
    "CD-Online - Issue 01 - Internet on TV (UK)": {
        "languages": "En"
    },
    "CD-Online - Issue 01 - Internet on TV (UK) (Rev 1)": {
        "languages": "En"
    },
    "CD-i Demodisc Fall 1996 & Spring 1997 (Europe)": {
        "languages": ""
    },
    "CD-i Demonstration Disc (USA)": {
        "languages": "En"
    },
    "CDI 450 - Tutorial Disc (Europe) (En,Fr,De,Es,It,Nl,Pt)": {
        "languages": "Nl, En, Fr, De, It, Pt, Es"
    },
    "CDI 470 - Tutorial Disc (Europe) (En,Fr,De,Es,It,Nl,Pt,Sv,No,Da,Fi)": {
        "languages": "Da, Nl, En, Fi, Fr, De, It, No, Pt, Es, Sv"
    },
    "Caesars World of Boxing (Europe)": {
        "languages": "En"
    },
    "Caesars World of Boxing (USA)": {
        "languages": "En"
    },
    "Caesars World of Gambling (USA, Europe)": {
        "languages": "En"
    },
    "Caraibes Offshore (France)": {
        "languages": ""
    },
    "Caricature (Europe)": {
        "languages": ""
    },
    "Cartoon Jukebox (France)": {
        "languages": "Fr"
    },
    "Cartoon Jukebox (Germany)": {
        "languages": ""
    },
    "Cartoon Jukebox (Italy)": {
        "languages": "It"
    },
    "Cartoon Jukebox (Netherlands)": {
        "languages": ""
    },
    "Cartoon Jukebox (USA, Europe)": {
        "languages": "En"
    },
    "Chaos Control (Europe)": {
        "languages": "En"
    },
    "Chaos Control (Europe) (Rev 1)": {
        "languages": "En"
    },
    "Chaos Control (France)": {
        "languages": "Fr"
    },
    "Chaos Control (France) (Demo)": {
        "languages": ""
    },
    "Chaos Control (Germany)": {
        "languages": "De"
    },
    "Child is Born, A (USA)": {
        "languages": "En"
    },
    "Children's Musical Theatre (France)": {
        "languages": "En"
    },
    "Christmas Crisis (Europe)": {
        "languages": ""
    },
    "Cistercian Architecture (Europe) (En,Fr,De) (19931104)": {
        "languages": "En, Fr, De"
    },
    "Cistercian Architecture (Europe) (En,Fr,De) (19940323)": {
        "languages": "En, Fr, De"
    },
    "Citta piu Felice del Mondo! di Richard Scarry, La (Italy)": {
        "languages": "It"
    },
    "Classical Guitar (USA)": {
        "languages": "En"
    },
    "Classical Jukebox (USA)": {
        "languages": ""
    },
    "Cluedo (Europe)": {
        "languages": "En"
    },
    "Cluedo - The Mystery Continues (Europe)": {
        "languages": "En"
    },
    "Complete Your Financial Jigsaw (UK)": {
        "languages": ""
    },
    "Compton's Interactive Encyclopedia (Europe)": {
        "languages": "En"
    },
    "Compton's Interactive Encyclopedia (USA)": {
        "languages": "En"
    },
    "Connect Four (Europe)": {
        "languages": "En"
    },
    "Cranberries, The - Doors and Windows (Europe)": {
        "languages": "En"
    },
    "Cranberries, The - Doors and Windows (USA)": {
        "languages": "En"
    },
    "Cream of Eric Clapton, The (Europe) (Disc 1)": {
        "languages": ""
    },
    "Cream of Eric Clapton, The (Europe) (Disc 2)": {
        "languages": ""
    },
    "Creature Shock (Europe) (Disc 1)": {
        "languages": "En"
    },
    "Creature Shock (Europe) (Disc 2)": {
        "languages": "En"
    },
    "Crime Patrol (Europe)": {
        "languages": "En"
    },
    "Cure - Show (Europe) (Disc 1)": {
        "languages": "En"
    },
    "Cure - Show (Europe) (Disc 2)": {
        "languages": "En"
    },
    "Dark Castle (Europe)": {
        "languages": "En"
    },
    "Dark Fables of Aesop, The (USA)": {
        "languages": "En"
    },
    "Dave Grusin - The Gershwin Connection (Europe)": {
        "languages": "En"
    },
    "Dave Grusin - The Gershwin Connection (USA)": {
        "languages": ""
    },
    "Defender of the Crown (USA, Europe)": {
        "languages": "En"
    },
    "Destination Great Britain - Central and Northern England (Canada)": {
        "languages": ""
    },
    "Destination Great Britain - England's West Country (Canada)": {
        "languages": ""
    },
    "Destination Great Britain - London and Southern England (Canada)": {
        "languages": ""
    },
    "Destination Great Britain - Wales (Canada)": {
        "languages": ""
    },
    "Dictionnaire Hachette Multimedia (France)": {
        "languages": "Fr"
    },
    "Dictionnaire Hachette Multimedia (France) (Rerelease)": {
        "languages": "Fr"
    },
    "Digital Video Demonstration Disc (USA)": {
        "languages": ""
    },
    "Dimo's Quest (Europe)": {
        "languages": "En"
    },
    "Dimo's Quest (USA)": {
        "languages": "En"
    },
    "Discovering Pompei (Europe) (En,Fr)": {
        "languages": "En, Fr"
    },
    "Dizionario Universale Multimediale Grolier Hachette (Italy) (Demo)": {
        "languages": "It"
    },
    "Do You Remember the '60s (UK)": {
        "languages": "En"
    },
    "Domino (Netherlands)": {
        "languages": ""
    },
    "Downhome Blues, The (USA)": {
        "languages": "En"
    },
    "Dragon's Lair (Europe)": {
        "languages": "En"
    },
    "Dragon's Lair (USA)": {
        "languages": "En"
    },
    "Dragon's Lair II - Time Warp (Europe)": {
        "languages": "En"
    },
    "Dragon's Lair II - Time Warp (USA)": {
        "languages": "En"
    },
    "Drug Wars (Europe)": {
        "languages": "En"
    },
    "Earth Command (Germany)": {
        "languages": "De"
    },
    "Earth Command (Netherlands)": {
        "languages": "Nl"
    },
    "Enkhuizer Almanak 1997 (Netherlands)": {
        "languages": "Nl"
    },
    "Escape from CyberCity (USA, Europe)": {
        "languages": "En"
    },
    "Exit 7 - The Harley-Davidson Experience on CD-i (USA)": {
        "languages": "En"
    },
    "Explorations of Space (USA)": {
        "languages": ""
    },
    "Face Kitchen (UK)": {
        "languages": ""
    },
    "Face Kitchen (UK) (Proto)": {
        "languages": ""
    },
    "Family Games I (Europe)": {
        "languages": "En"
    },
    "Family Games I (Europe) (Rev 1)": {
        "languages": "En"
    },
    "Family Games II - Junkfood Jive (Europe)": {
        "languages": "En"
    },
    "Flashback (Europe)": {
        "languages": "En"
    },
    "Flashback (Europe) (Proto)": {
        "languages": ""
    },
    "Flintstones-Jetsons Timewarp (Europe)": {
        "languages": "En"
    },
    "Forbidden City, The (Europe)": {
        "languages": "En"
    },
    "Getting Ahead - Making Time (Europe)": {
        "languages": "En"
    },
    "Getting Ahead - Managing Your Boss (Europe)": {
        "languages": "En"
    },
    "Getting Ahead - Money at Work (Europe)": {
        "languages": "En"
    },
    "Getting Ahead - Presentation Skills (Europe)": {
        "languages": "En"
    },
    "Gifts to Behold (USA) (En,Ja,Fr,De,Es,It,Nl)": {
        "languages": "Nl, En, Fr, De, It, Ja, Es"
    },
    "Girl's Club (Europe)": {
        "languages": "En"
    },
    "Gli Impressionisti Francesi (Italy)": {
        "languages": "It"
    },
    "Go - Special Edition (USA) (Unl)": {
        "languages": ""
    },
    "Golden Oldies Jukebox (Europe)": {
        "languages": "En"
    },
    "Golden Oldies Jukebox (USA) (19910827)": {
        "languages": ""
    },
    "Golden Oldies Jukebox (USA) (19910917)": {
        "languages": "En"
    },
    "Golf My Way (USA) (Disc 1)": {
        "languages": "En"
    },
    "Golf My Way (USA) (Disc 2)": {
        "languages": "En"
    },
    "Golf My Way (USA) (Disc 3)": {
        "languages": "En"
    },
    "Golf My Way (USA) (Disc 4)": {
        "languages": "En"
    },
    "Golf My Way (USA) (Disc 5)": {
        "languages": "En"
    },
    "Great Day at the Races, A (Europe)": {
        "languages": "En"
    },
    "Great Day at the Races, A (USA)": {
        "languages": "En"
    },
    "Hanna-Barbera Cartoon Carnival (USA, Europe)": {
        "languages": "En"
    },
    "Hans Christian Andersen's Thumbelina (Europe)": {
        "languages": "En"
    },
    "Harvest of the Sun (Europe)": {
        "languages": ""
    },
    "Harvest of the Sun - Van Gogh (USA)": {
        "languages": ""
    },
    "Harvest of the Sun - Van Gogh - Une Moisson de Soleils (France)": {
        "languages": "Fr"
    },
    "Historia del Arte Espanol (Spain) (Disc 1) (Los Origenes - Prehistoria y Primeras Civilizaciones)": {
        "languages": "Es"
    },
    "Historia del Arte Espanol (Spain) (Disc 10) (El Siglo de los Creadores - Vanguardia y Tradicion en el Alba de un Milenio)": {
        "languages": "Es"
    },
    "Historia del Arte Espanol (Spain) (Disc 2) (Imperio y Religion - Del Mundo Romano al Prerromanico)": {
        "languages": "Es"
    },
    "Historia del Arte Espanol (Spain) (Disc 3) (Cristol de Tres Culturas - Lo Islamico, lo Judio y lo Cristiano)": {
        "languages": "Es"
    },
    "Historia del Arte Espanol (Spain) (Disc 4) (La Epoca de los Monasterios - La Plenitud del Romanico)": {
        "languages": "Es"
    },
    "Historia del Arte Espanol (Spain) (Disc 5) (La Epoca de las Catedrales - El Esplendor del Gotico)": {
        "languages": "Es"
    },
    "Historia del Arte Espanol (Spain) (Disc 6) (La Espana Imperial - Renacimiento y Humanismo)": {
        "languages": "Es"
    },
    "Historia del Arte Espanol (Spain) (Disc 7) (El Siglo de Oro - El Sentimiento de lo Barroco)": {
        "languages": "Es"
    },
    "Historia del Arte Espanol (Spain) (Disc 8) (El Siglo de las Luces - Illustrados, Neoclasicos y Academicos)": {
        "languages": "Es"
    },
    "Historia del Arte Espanol (Spain) (Disc 9) (La Epoca de las Revoluciones - De Goya a la Modernidad)": {
        "languages": "Es"
    },
    "Hollandse Meesters uit de Zeventiende Eeuw (Netherlands)": {
        "languages": "Nl"
    },
    "Hondenliefde (Netherlands)": {
        "languages": "Nl"
    },
    "Hondenliefde (Netherlands) (Beta)": {
        "languages": ""
    },
    "Hot and Cold (Europe) (En,Fr)": {
        "languages": "En, Fr"
    },
    "Hotel Mario (Europe)": {
        "languages": "En"
    },
    "Hotel Mario (France)": {
        "languages": "Fr"
    },
    "How the Rhinoceros Got His Skin (Europe)": {
        "languages": "En"
    },
    "Hunt for Red October, The (USA) (Disc 1)": {
        "languages": "En"
    },
    "Hunt for Red October, The (USA) (Disc 2)": {
        "languages": "En"
    },
    "Impressionnistes Francais, Les (France)": {
        "languages": ""
    },
    "Inca (Europe) (En,Es,It,Pt)": {
        "languages": "En, It, Pt, Es"
    },
    "Inca (Europe) (En,Fr,De,Nl)": {
        "languages": "Nl, En, Fr, De"
    },
    "Inca (Europe) (En,Fr,De,Nl) (Rev 1)": {
        "languages": "Nl, En, Fr, De"
    },
    "Inca (USA)": {
        "languages": "En"
    },
    "Interactief Philips Magazine '92-'93 (Netherlands)": {
        "languages": "Nl"
    },
    "Interactive Education - Converting Fractions to Decimals (USA)": {
        "languages": "En"
    },
    "Interactive Education - Learning To Read - Action 1 (USA)": {
        "languages": "En"
    },
    "Interactive Education - Learning To Read - Action 2 (USA)": {
        "languages": "En"
    },
    "Interactive Education - Learning To Read - People 1 (USA)": {
        "languages": "En"
    },
    "Interactive Education - Multiplying & Dividing Fractions (USA)": {
        "languages": "En"
    },
    "Interactive Math - Decimals (USA) (En,Es)": {
        "languages": "En, Es"
    },
    "Interactive Math - Percentages (USA) (En,Es)": {
        "languages": "En, Es"
    },
    "Interactive Math - Whole Numbers (USA) (En,Es)": {
        "languages": "En, Es"
    },
    "International Tennis Open (Europe) (En,Fr) (8100082)": {
        "languages": "En, Fr"
    },
    "International Tennis Open (Europe) (En,Fr) (8120040)": {
        "languages": "En, Fr"
    },
    "International Tennis Open (Germany) (En,De)": {
        "languages": "En, De"
    },
    "International Tennis Open (Germany) (En,De) (Version 2 Spieler)": {
        "languages": "En, De"
    },
    "International Tennis Open (Italy) (En,It)": {
        "languages": "En, It"
    },
    "International Tennis Open (USA) (En,Fr)": {
        "languages": "En, Fr"
    },
    "Internetten op je TV! (Netherlands)": {
        "languages": "Nl"
    },
    "Introduction to Photo CD, An - Version 2.0 (USA)": {
        "languages": "En"
    },
    "Jan Pienkowski Haunted House (Europe) (En,Fr,De,Es,It,Nl)": {
        "languages": "Nl, En, Fr, De, It, Es"
    },
    "Jazz Giants - From Big Band to Bossa Nova (USA)": {
        "languages": "En"
    },
    "Je Parle l'Allemand - Junior (France)": {
        "languages": "De"
    },
    "Je Parle l'Anglais - Senior (France)": {
        "languages": "En"
    },
    "Jeopardy! (USA)": {
        "languages": "En"
    },
    "Jeopardy! (USA) (Demo)": {
        "languages": ""
    },
    "Jigsaw - The Ultimate Electronic Puzzle (Europe)": {
        "languages": "En"
    },
    "Jigsaw - The Ultimate Electronic Puzzle (Europe) (Rerelease)": {
        "languages": "En"
    },
    "Jigsaw - The Ultimate Electronic Puzzle (USA)": {
        "languages": "En"
    },
    "Joker's Wild! Jr., The (USA)": {
        "languages": ""
    },
    "Joker's Wild!, The (USA)": {
        "languages": ""
    },
    "Journal Interactif 94 et le Jeu des Stars de l'Info, Le (France) (Disque Bande Annonce)": {
        "languages": "Fr"
    },
    "Journeys Through Victorian London (UK)": {
        "languages": "En"
    },
    "Joy of Sex, The (Europe)": {
        "languages": "En"
    },
    "Joy of Sex, The (Europe) (Rev 1)": {
        "languages": "En"
    },
    "Karaoke Kids (Netherlands)": {
        "languages": "Nl"
    },
    "Karaoke Schlager 2 (Sweden)": {
        "languages": "Sv"
    },
    "Karaoke Vol. 1 (Netherlands)": {
        "languages": "Nl"
    },
    "Karaoke Vol. 2 (Netherlands)": {
        "languages": "Nl"
    },
    "Karaoke Vol. 3 (Netherlands)": {
        "languages": "Nl"
    },
    "Kathy Smith - Personal Trainer (USA)": {
        "languages": "En"
    },
    "Kether (Europe) (En,Fr)": {
        "languages": "En, Fr"
    },
    "Kether (Europe) (En,Fr) (Rev 1)": {
        "languages": "En, Fr"
    },
    "Kether (Germany) (En,De)": {
        "languages": "En, De"
    },
    "Kether (Netherlands) (En,Nl)": {
        "languages": "Nl, En"
    },
    "Kether (USA) (En,Fr)": {
        "languages": "En, Fr"
    },
    "Kingdom - The Far Reaches (Europe)": {
        "languages": "En"
    },
    "Kingdom - The Far Reaches (USA)": {
        "languages": "En"
    },
    "Kunstschatten van Rusland, De (Netherlands)": {
        "languages": ""
    },
    "Labyrinth von Kreta (Germany)": {
        "languages": "De"
    },
    "Language Director - English - Level 1 (Europe) (Disc 1)": {
        "languages": ""
    },
    "Language Director - English - Level 1 (Europe) (Disc 1) (Alt)": {
        "languages": ""
    },
    "Language Director - English - Level 1 (Europe) (Disc 2)": {
        "languages": ""
    },
    "Language Director - English - Level 1 (Europe) (Disc 2) (Rerelease)": {
        "languages": ""
    },
    "Language Director - English - Level 2 (Europe) (Disc 1)": {
        "languages": ""
    },
    "Language Director - English - Level 2 (Europe) (Disc 1) (Alt)": {
        "languages": ""
    },
    "Language Director - English - Level 2 (Europe) (Disc 2)": {
        "languages": ""
    },
    "Language Director - English - Level 2 (Europe) (Disc 2) (Alt)": {
        "languages": ""
    },
    "Language Director - English - Level 3 (Europe) (Disc 1)": {
        "languages": ""
    },
    "Language Director - English - Level 3 (Europe) (Disc 2)": {
        "languages": ""
    },
    "Language Director - Guided Tour - English Level 1 (Europe)": {
        "languages": ""
    },
    "Language Director - Guided Tour - English Level 1 (Europe) (Rerelease)": {
        "languages": ""
    },
    "Language Director - Guided Tour - English Level 2 (Europe)": {
        "languages": ""
    },
    "Language Director - Guided Tour - English Level 3 (Europe)": {
        "languages": ""
    },
    "Laser Lords (Europe)": {
        "languages": "En"
    },
    "Laser Lords (Germany)": {
        "languages": "De"
    },
    "Laser Lords (Netherlands)": {
        "languages": "Nl"
    },
    "Last Bounty Hunter, The (Europe)": {
        "languages": "En"
    },
    "Lemmings (Europe)": {
        "languages": "En"
    },
    "Lettergreep (Netherlands)": {
        "languages": "Nl"
    },
    "Lingo (Netherlands)": {
        "languages": "Nl"
    },
    "Link - The Faces of Evil (Europe)": {
        "languages": "En"
    },
    "Link - The Faces of Evil (France)": {
        "languages": "Fr"
    },
    "Link - The Faces of Evil (USA)": {
        "languages": "En"
    },
    "Litil Divil (Europe)": {
        "languages": "En"
    },
    "Live Without Monty Python (Europe)": {
        "languages": ""
    },
    "Lords of the Rising Sun (Europe)": {
        "languages": "En"
    },
    "Lords of the Rising Sun (USA)": {
        "languages": "En"
    },
    "Lost Eden (Europe)": {
        "languages": "En"
    },
    "Lost Eden (France)": {
        "languages": "Fr"
    },
    "Lost Eden (Germany)": {
        "languages": "De"
    },
    "Lost Eden (Netherlands)": {
        "languages": "Nl"
    },
    "Lost Ride, The (Europe)": {
        "languages": "En"
    },
    "Louis Armstrong - An American Songbook (Europe)": {
        "languages": "En"
    },
    "Lucky Luke - The Video Game (Europe)": {
        "languages": ""
    },
    "Macchina delle Favole, La - Racconti Spaziali (Italy)": {
        "languages": "It"
    },
    "Macchina delle Favole, La - Racconti di Magia (Italy)": {
        "languages": "It"
    },
    "Machine a Remonter le Temps, La (France)": {
        "languages": "Fr"
    },
    "Mad Dog II - The Lost Gold (Europe)": {
        "languages": "En"
    },
    "Mad Dog McCree (Europe) (Alt)": {
        "languages": "En"
    },
    "Mad Dog McCree (Germany)": {
        "languages": "De"
    },
    "Mad Dog McCree (Italy)": {
        "languages": "It"
    },
    "Mad Dog McCree (USA, Europe)": {
        "languages": "En"
    },
    "Maestri Olandesi del Seicento, I (Italy)": {
        "languages": "It"
    },
    "Making the Grade (UK)": {
        "languages": "En"
    },
    "Malarskolan (Sweden) (En,Fr,De,Es,It,Sv)": {
        "languages": "En, Fr, De, It, Es, Sv"
    },
    "Manna Space - Travel Business (Japan)": {
        "languages": "Ja"
    },
    "Marco Polo (Europe) (Disc 1) (The Game)": {
        "languages": "En"
    },
    "Marco Polo (Europe) (Disc 2) (The Documentation)": {
        "languages": "En"
    },
    "Marco Polo (France) (Disc 1) (Le Jeu)": {
        "languages": "Fr"
    },
    "Marco Polo (France) (Disc 2) (La Documentation)": {
        "languages": "Fr"
    },
    "Master Labyrinth (Europe) (En,Fr,De,Nl)": {
        "languages": "Nl, En, Fr, De"
    },
    "Master Labyrinth (Germany) (En,Fr,De,Nl)": {
        "languages": "Nl, En, Fr, De"
    },
    "Mathtrak K1 (USA)": {
        "languages": ""
    },
    "Max Magic (USA)": {
        "languages": ""
    },
    "Mega Maze (Europe)": {
        "languages": "En"
    },
    "Mega Maze (Europe) (Proto)": {
        "languages": ""
    },
    "Memory Works, The - For Names and Faces (USA)": {
        "languages": ""
    },
    "Mercer Mayer's Little Monster at School (USA)": {
        "languages": "En"
    },
    "Merlin's Apprentice (Europe)": {
        "languages": "En"
    },
    "Merlin's Apprentice (USA)": {
        "languages": "En"
    },
    "Merlin's Apprentice (USA) (v1.11)": {
        "languages": "En"
    },
    "Micro Machines (Europe)": {
        "languages": "En"
    },
    "Micro Machines (Europe) (Demo)": {
        "languages": "En"
    },
    "Monty Python's Invasion from the Planet Skyron (Europe)": {
        "languages": "En"
    },
    "Monty Python's Invasion from the Planet Skyron (Europe) (Proto)": {
        "languages": ""
    },
    "Monty Python's More Naughty Bits (Europe)": {
        "languages": ""
    },
    "Mother Goose - Hidden Pictures (USA)": {
        "languages": "En"
    },
    "Mother Goose - Rhymes to Color (Europe)": {
        "languages": "En"
    },
    "Mozart - La Vita e la Musica (Italy)": {
        "languages": "It"
    },
    "Mutant Rampage - Bodyslam (Europe)": {
        "languages": "En"
    },
    "Muzzy (Europe)": {
        "languages": ""
    },
    "Myst (Europe)": {
        "languages": "En"
    },
    "Mystic Midway - Phantom Express (Europe)": {
        "languages": "En"
    },
    "Mystic Midway - Phantom Express (USA)": {
        "languages": "En"
    },
    "Mystic Midway - Rest in Pieces (USA, Europe)": {
        "languages": "En"
    },
    "NFL 100 Greatest Touchdowns (USA)": {
        "languages": "En"
    },
    "NFL Football Trivia Challenge (USA)": {
        "languages": ""
    },
    "NFL Hall of Fame Football (USA) (19940914)": {
        "languages": ""
    },
    "NFL Hall of Fame Football (USA) (19941014)": {
        "languages": "En"
    },
    "NFL Instant Replay (USA)": {
        "languages": "En"
    },
    "Naftaline chez Elle (France)": {
        "languages": "Fr"
    },
    "Name That Tune (USA)": {
        "languages": ""
    },
    "Nasce un Bambino (Italy)": {
        "languages": "It"
    },
    "Nationale Muziekkado 1995, Het (Netherlands)": {
        "languages": "Nl"
    },
    "Nature Under Threat (Europe)": {
        "languages": "En"
    },
    "Nederlands Elftal Compleet (Netherlands)": {
        "languages": "Nl"
    },
    "Nederlands Film Festival '95 (Netherlands)": {
        "languages": "Nl"
    },
    "Night in Nylon City, A (Europe)": {
        "languages": ""
    },
    "Noah's Ark (USA)": {
        "languages": ""
    },
    "Ontdek het Onbekende Nederland (Netherlands)": {
        "languages": "Nl"
    },
    "Oogst van de Zon (Netherlands)": {
        "languages": ""
    },
    "Op Jacht naar Vernuft (Netherlands) (En,Nl)": {
        "languages": "Nl, En"
    },
    "Open de Palm Springs, L' (France)": {
        "languages": "Fr"
    },
    "Origami (Europe)": {
        "languages": ""
    },
    "Othello (Europe)": {
        "languages": ""
    },
    "Ours Berenstain, Les - Comme des Grands (France)": {
        "languages": "Fr"
    },
    "Pac-Panic (Europe)": {
        "languages": "En"
    },
    "Page & Moy Ltd - Cruise Directory (UK)": {
        "languages": "En"
    },
    "Paint School I (Europe) (En,Fr,De,Es,It,Nl)": {
        "languages": "Nl, En, Fr, De, It, Es"
    },
    "Paint School I (USA)": {
        "languages": "En"
    },
    "Paint School II (Europe) (En,Fr,De,Es,It,Nl)": {
        "languages": "Nl, En, Fr, De, It, Es"
    },
    "Paint School II (USA)": {
        "languages": "En"
    },
    "Palm Springs Open, The (Germany)": {
        "languages": "De"
    },
    "Palm Springs Open, The (Italy)": {
        "languages": "It"
    },
    "Palm Springs Open, The (USA)": {
        "languages": ""
    },
    "Palm Springs Open, The (USA, Europe)": {
        "languages": "En"
    },
    "Patriot Games (USA) (Disc 1)": {
        "languages": "En"
    },
    "Patriot Games (USA) (Disc 2)": {
        "languages": "En"
    },
    "Pavarotti - O Sole Mio (Europe)": {
        "languages": "En"
    },
    "Pavarotti - O Sole Mio (USA)": {
        "languages": ""
    },
    "Pecos Bill (Europe)": {
        "languages": "En"
    },
    "Pecos Bill (Italy) (En,It)": {
        "languages": "En, It"
    },
    "Pecos Bill (USA)": {
        "languages": "En"
    },
    "Pete Townshend Live (USA) (Demo)": {
        "languages": "En"
    },
    "Peugeot 406 en Val de Loire, La (France)": {
        "languages": "Fr"
    },
    "Philips (Europe)": {
        "languages": ""
    },
    "Philips Audio-Video Products '92-'93 on CD-Interactive (Europe) (En,Fr,De,Es,It,Nl)": {
        "languages": "Nl, En, Fr, De, It, Es"
    },
    "Philips Media Interactieve Encyclopedie (Netherlands)": {
        "languages": "Nl"
    },
    "Philips Media Interactieve Encyclopedie (Netherlands) (Demo)": {
        "languages": "Nl"
    },
    "Photo CD Sample Disc (USA)": {
        "languages": ""
    },
    "Pinball (Europe) (Alt)": {
        "languages": "En"
    },
    "Pinball (USA, Europe)": {
        "languages": "En"
    },
    "Playboy's Complete Massage (France)": {
        "languages": ""
    },
    "Portrait d'une Ville - Venise (France)": {
        "languages": "Fr"
    },
    "Portrait of a City - Venice (Europe)": {
        "languages": "En"
    },
    "Posse (USA) (Disc 1)": {
        "languages": ""
    },
    "Posse (USA) (Disc 2)": {
        "languages": ""
    },
    "Power Hitter (Europe)": {
        "languages": "En"
    },
    "Power Hitter (Europe) (Rev 1)": {
        "languages": "En"
    },
    "Power Hitter (USA)": {
        "languages": ""
    },
    "Power Match (Europe)": {
        "languages": ""
    },
    "Prelude (France) (En,Ja,Fr,It,Nl)": {
        "languages": "Nl, En, Fr, It, Ja"
    },
    "Prelude (USA) (En,Ja,Fr,De,Es,It,Nl)": {
        "languages": "Nl, En, Fr, De, It, Ja, Es"
    },
    "Premiere Collection Encore, The - Andrew Lloyd Webber (USA)": {
        "languages": ""
    },
    "Private Lesson Series - Jazz Guitar (Europe)": {
        "languages": "En"
    },
    "Pyramid Adventures - Episode 1 - Treasures of the Lost Pyramid (USA)": {
        "languages": ""
    },
    "QuizMania (Italy)": {
        "languages": "It"
    },
    "Raccolto del Sole, Il - Van Gogh (Italy)": {
        "languages": "It"
    },
    "Reihe Privatunterricht - Die klassische Gitarre (Germany)": {
        "languages": ""
    },
    "Reihe Privatunterricht - Rockgitarre - Eine Anleitung fuer Anfaenger (Germany)": {
        "languages": "De"
    },
    "Rembrandt - His Art and the Music of His Era (USA)": {
        "languages": ""
    },
    "Renaissance in Florenz, Die (Germany)": {
        "languages": "De"
    },
    "Renaissance of Florence, The (USA)": {
        "languages": ""
    },
    "Renaissance van Florence, De (Netherlands)": {
        "languages": ""
    },
    "Revolution in Color, A (Europe)": {
        "languages": "En"
    },
    "Rhythm Maker (USA)": {
        "languages": "En"
    },
    "Richard Scarry's Allerbeste Buurt Disc! (Netherlands)": {
        "languages": "Nl"
    },
    "Richard Scarry's Allerdrukste Buurt Disc! (Netherlands)": {
        "languages": "Nl"
    },
    "Richard Scarry's Best Neighborhood Disc Ever! (Europe) (Rerelease)": {
        "languages": ""
    },
    "Rinascimento a Firenze, Il (Italy)": {
        "languages": "It"
    },
    "Rise of the Robots (Europe)": {
        "languages": "En"
    },
    "Rise of the Robots (Europe) (Alt)": {
        "languages": "En"
    },
    "Ritratto di Citta - Venezia (Italy)": {
        "languages": "It"
    },
    "Rock Guitar - A Beginner's Guide (Europe)": {
        "languages": ""
    },
    "Royal Classics CDi Sampler - The Classics You Love (Europe)": {
        "languages": "En"
    },
    "Saelis Cirkus Aeventyr (Sweden)": {
        "languages": ""
    },
    "Sail to Win! A Rules and Tactics Challenge (Europe)": {
        "languages": ""
    },
    "Sailing (USA)": {
        "languages": "En"
    },
    "Sandy's Circus Adventure (USA)": {
        "languages": "En"
    },
    "Sandy's Circus Avontuur (Netherlands)": {
        "languages": "Nl"
    },
    "Sargon Chess (Europe)": {
        "languages": "En"
    },
    "Schtroumpfs, Les - Le Teleportaschtroumpf (France)": {
        "languages": "Fr"
    },
    "Scotland Yard Interactif (France)": {
        "languages": ""
    },
    "Scotland Yard Interactive (Germany)": {
        "languages": "De"
    },
    "Secret Mission (France)": {
        "languages": ""
    },
    "Secret Mission (Netherlands)": {
        "languages": ""
    },
    "Shadoan (Europe)": {
        "languages": ""
    },
    "Shark Alert (USA)": {
        "languages": ""
    },
    "Shipwreck (Europe)": {
        "languages": "En"
    },
    "Shorelines (USA)": {
        "languages": ""
    },
    "Solar System (Europe)": {
        "languages": "En"
    },
    "Somewhere - Une Envie de Naturel (France)": {
        "languages": "Fr"
    },
    "Souris du Pere Noel, Les (France)": {
        "languages": ""
    },
    "Space Ace (Europe)": {
        "languages": "En"
    },
    "Sport Freaks (Netherlands)": {
        "languages": "Nl"
    },
    "St. Petersbourg et les Tresors de l'Ermitage - The Art of the Czars (France)": {
        "languages": "Fr"
    },
    "Star Trek VI - The Undiscovered Country (Europe) (Disc 1)": {
        "languages": ""
    },
    "Star Trek VI - The Undiscovered Country (Europe) (Disc 2)": {
        "languages": ""
    },
    "Steel Machine (Europe)": {
        "languages": ""
    },
    "Stickybear Maths (Europe) (En,Es)": {
        "languages": "En, Es"
    },
    "Stickybear Preschool (USA)": {
        "languages": ""
    },
    "Sting - Ten Summoner's Tales (Europe)": {
        "languages": "En"
    },
    "Story Machine - Magic Tales (Europe)": {
        "languages": "En"
    },
    "Story Machine - Magic Tales (USA)": {
        "languages": "En"
    },
    "Striker Pro (Europe)": {
        "languages": "En"
    },
    "Striker Pro (USA)": {
        "languages": ""
    },
    "Strip Poker Live (Italy) (En,It)": {
        "languages": "En, It"
    },
    "Strip-Poker Pro (France) (En,Fr)": {
        "languages": "En, Fr"
    },
    "Stunde der Patrioten, Die (Germany) (Disc 1)": {
        "languages": "De"
    },
    "Stunde der Patrioten, Die (Germany) (Disc 2)": {
        "languages": "De"
    },
    "SuperTest (Europe) (De,It)": {
        "languages": "De, It"
    },
    "Surf City (Europe)": {
        "languages": "En"
    },
    "Surf City (USA)": {
        "languages": ""
    },
    "TF1 - Le Journal Interactif 1995 et le Jeu des Stars de l'Info (France) (Disc 1) (Le Journal Interactif 1995)": {
        "languages": "Fr"
    },
    "TF1 - Le Journal Interactif 1995 et le Jeu des Stars de l'Info (France) (Disc 2) (Le Jeu des Stars de l'Info)": {
        "languages": "Fr"
    },
    "TF1 - Le Journal Interactif 94 et le Jeu des Stars de l'Info (France) (Disc 1) (Le Journal Interactif 94)": {
        "languages": "Fr"
    },
    "TF1 - Le Journal Interactif 94 et le Jeu des Stars de l'Info (France) (Disc 2) (Le Jeu des Stars de l'Info)": {
        "languages": "Fr"
    },
    "TR-I - No World Order (Europe)": {
        "languages": "En"
    },
    "TR-I - No World Order (USA)": {
        "languages": "En"
    },
    "Tangram (Europe) (En,Ja,Fr,De,Es,It,Nl,Pt)": {
        "languages": "Nl, En, Fr, De, It, Ja, Pt, Es"
    },
    "Tangram (Europe) (En,Ja,Fr,De,Es,It,Nl,Pt) (Beta)": {
        "languages": "Nl, En, Fr, De, It, Ja, Pt, Es"
    },
    "Tell Me Why - Two (Europe)": {
        "languages": "En"
    },
    "Tesoro dell'Isola dei Giochi, Il (Italy)": {
        "languages": "It"
    },
    "Test Codoroute I (France)": {
        "languages": "Fr"
    },
    "Test Codoroute II (France)": {
        "languages": "Fr"
    },
    "Tetris (USA) (Beta)": {
        "languages": "En"
    },
    "Tetris (USA, Europe)": {
        "languages": "En"
    },
    "Text Tiles (USA, Europe)": {
        "languages": "En"
    },
    "Thunder in Paradise (Europe) (Disc 1) (The Game)": {
        "languages": "En"
    },
    "Thunder in Paradise (Germany)": {
        "languages": "De"
    },
    "Thunder in Paradise (USA) (Disc 1) (The Game)": {
        "languages": ""
    },
    "Tim & Beer in het Ziekenhuis (Netherlands)": {
        "languages": "Nl"
    },
    "Tim & Beer op het Vliegveld (Netherlands)": {
        "languages": "Nl"
    },
    "Tim et Ted - A l' Hopital (France)": {
        "languages": "Fr"
    },
    "Tim et Ted a l'Aeroport (France)": {
        "languages": "Fr"
    },
    "Tim et Ted au Cinema (France)": {
        "languages": "Fr"
    },
    "Tim et Ted au Port (France)": {
        "languages": "Fr"
    },
    "Time Life Photography (Europe)": {
        "languages": ""
    },
    "Time Life Presenta - La Fotografia in 35mm (Italy)": {
        "languages": "It"
    },
    "Time Life Presente - La Photographie 24 x 36 mm (France)": {
        "languages": "Fr"
    },
    "Time Life Presents - 35mm Photography (USA)": {
        "languages": ""
    },
    "Time Life Presents - 35mm Photography (USA) (Alt)": {
        "languages": ""
    },
    "Titanic - An Interactive Exploration (USA)": {
        "languages": "En"
    },
    "Tom - Il Dizionario Magico (Italy) (En,Fr,It)": {
        "languages": "En, Fr, It"
    },
    "Top Gun (Germany) (Disc 1)": {
        "languages": "De"
    },
    "Top Gun (Germany) (Disc 2)": {
        "languages": "De"
    },
    "Top Gun (USA) (Disc 1)": {
        "languages": "En"
    },
    "Top Gun (USA) (Disc 2)": {
        "languages": "En"
    },
    "Treasures of the Smithsonian (USA, Europe)": {
        "languages": "En"
    },
    "Tresor de l'Ile aux Jeux, Le (France)": {
        "languages": "Fr"
    },
    "UEFA Champions League 95-96 (Italy)": {
        "languages": "It"
    },
    "USA '94 World Cup (Europe)": {
        "languages": ""
    },
    "USA '94 World Cup (Europe) (En,Es,It)": {
        "languages": "En, It, Es"
    },
    "Ultimate Noah's Ark, The (UK)": {
        "languages": "En"
    },
    "Ultra CD-i Soccer (Europe)": {
        "languages": "En"
    },
    "Universal CD-ROM - New Age Interactive 12.8 (Italy) (En,It)": {
        "languages": "En, It"
    },
    "Universal CD-ROM - New Age Television 5.1 (Italy)": {
        "languages": "It"
    },
    "Uptown Blues, The (USA)": {
        "languages": "En"
    },
    "Verhaengnisvolle Affaere, Eine (Germany) (Disc 1)": {
        "languages": "De"
    },
    "Verhaengnisvolle Affaere, Eine (Germany) (Disc 2)": {
        "languages": "De"
    },
    "Video Speedway - Grand Prix (France)": {
        "languages": "Fr"
    },
    "Video Speedway - The Ultimate Racing Experience (Europe)": {
        "languages": "En"
    },
    "Video Speedway - The Ultimate Racing Experience (USA)": {
        "languages": "En"
    },
    "Ville Surprise de Richard Scarry 1, La (France)": {
        "languages": "Fr"
    },
    "Ville Surprise de Richard Scarry 2, La (France)": {
        "languages": "Fr"
    },
    "Vins de France, Les (France)": {
        "languages": "Fr"
    },
    "Visit to Sesame Street, A - Letters (USA) (19910913)": {
        "languages": ""
    },
    "Visit to Sesame Street, A - Letters (USA) (19920225)": {
        "languages": "En"
    },
    "Visit to Sesame Street, A - Numbers (USA)": {
        "languages": ""
    },
    "Vliegende Hollander, De (Netherlands)": {
        "languages": "Nl"
    },
    "Voetbal (Netherlands)": {
        "languages": "Nl"
    },
    "Von der Elbe an die Spree (Germany)": {
        "languages": "De"
    },
    "Voyeur (USA)": {
        "languages": "En"
    },
    "Voyeur ...Don't Get Caught (Europe)": {
        "languages": "En"
    },
    "Voyeur ...lass Dich nicht erwischen! (Germany)": {
        "languages": "De"
    },
    "Wacky World of Miniature Golf with Eugene Levy, The (USA)": {
        "languages": "En"
    },
    "Weather Kitchen, The (USA)": {
        "languages": ""
    },
    "What's That Bird Britain and Europe (Europe) (En,Fr,De,Es,It)": {
        "languages": "En, Fr, De, It, Es"
    },
    "Who Shot Johnny Rock (Europe)": {
        "languages": "En"
    },
    "Who Shot Johnny Rock (France)": {
        "languages": "Fr"
    },
    "Who Shot Johnny Rock (USA)": {
        "languages": "En"
    },
    "Wie das Rhinozeros zu seiner Haut Kam (Germany)": {
        "languages": "De"
    },
    "Wordplay (Europe)": {
        "languages": "En"
    },
    "World Communities (USA)": {
        "languages": ""
    },
    "World Cup Golf (Europe) (En,Fr,De)": {
        "languages": "En, Fr, De"
    },
    "World of Impressionism, The (Europe)": {
        "languages": "En"
    },
    "Xplora 1 - Peter Gabriel's Secret World (Europe)": {
        "languages": "En"
    },
    "Yearn2Learn - Peanuts (Europe) (En,Fr,De,Nl)": {
        "languages": "Nl, En, Fr, De"
    },
    "Zelda - Der Zauberstab von Gamelon (Germany)": {
        "languages": "De"
    },
    "Zelda - The Wand of Gamelon (Europe)": {
        "languages": "En"
    },
    "Zelda - The Wand of Gamelon (France)": {
        "languages": "Fr"
    },
    "Zelda's Adventure (Europe)": {
        "languages": "En"
    },
    "Zenith (Europe)": {
        "languages": "En"
    },
    "Zombie Dinos from Planet Zeltoid (Europe)": {
        "languages": "En"
    },
    "Zombie Dinos from Planet Zeltoid (USA, Europe) (Rev 1)": {
        "languages": "En"
    },
    "Zombie Dinos vom Planeten Zeltoid (Germany)": {
        "languages": "De"
    },
    "Zoo... Eenvoudig - Dierenencyclopedie (Netherlands)": {
        "languages": "Nl"
    }
}
