{
	"Action Hero 3D - Wild Dog & IMICRO3D (Brazil) (Es,Pt)": {
		"languages": "Es,Pt"
	},
	"Alice no Pais das Maravilhas (Brazil) (Es,Pt)": {
		"languages": "Es,Pt"
	},
	"Alien Breaker Deluxe (Brazil) (Es,Pt)": {
		"languages": "Es,Pt"
	},
	"Alpine Racer (Brazil) (Es,Pt)": {
		"languages": "Es,Pt"
	},
	"Armageddon Squadron (Brazil) (Es,Pt)": {
		"languages": "Es,Pt"
	},
	"Bad Dudes vs. DragonNinja (Brazil) (Es,Pt)": {
		"languages": "Es,Pt"
	},
	"Bejeweled Twist (Brazil) (Es,Pt)": {
		"languages": "Es,Pt"
	},
	"Caveman Ninja (Brazil) (Es,Pt)": {
		"languages": "Es,Pt"
	},
	"Crash Bandicoot Nitro Kart 3D (Brazil) (Es,Pt)": {
		"languages": "Es,Pt"
	},
	"Dark Seal (Brazil) (Es,Pt)": {
		"languages": "Es,Pt"
	},
	"Disney All Star Cards (Brazil) (Es,Pt)": {
		"languages": "Es,Pt"
	},
	"Double Dragon (Brazil) (Es,Pt)": {
		"languages": "Es,Pt"
	},
	"FIFA 09 (Brazil) (Es,Pt)": {
		"languages": "Es,Pt"
	},
	"Galaxy on Fire (Brazil) (Es,Pt)": {
		"languages": "Es,Pt"
	},
	"Heavy Barrel (Brazil) (Es,Pt)": {
		"languages": "Es,Pt"
	},
	"Heavy Weapon (Brazil) (Es,Pt)": {
		"languages": "Es,Pt"
	},
	"Iron Sight (Brazil) (Es,Pt)": {
		"languages": "Es,Pt"
	},
	"Karnov's Revenge (Brazil) (Es,Pt)": {
		"languages": "Es,Pt"
	},
	"Magical Drop III (Brazil) (Es,Pt)": {
		"languages": "Es,Pt"
	},
	"Need For Speed - Carbon - Domine a Cidade (Brazil) (Es,Pt)": {
		"languages": "Es,Pt"
	},
	"Pac-Mania (Brazil) (Es,Pt)": {
		"languages": "Es,Pt"
	},
	"Peggle (Brazil) (Es,Pt)": {
		"languages": "Es,Pt"
	},
	"Powerboat Challenge (Brazil) (Es,Pt)": {
		"languages": "Es,Pt"
	},
	"Prey Evil (Brazil) (Es,Pt)": {
		"languages": "Es,Pt"
	},
	"Quake (Brazil) (Es,Pt)": {
		"languages": "Es,Pt"
	},
	"Quake II (Brazil) (Es,Pt)": {
		"languages": "Es,Pt"
	},
	"Raging Thunder 2 (Brazil) (Es,Pt)": {
		"languages": "Es,Pt"
	},
	"Rally Master Pro (Brazil) (Es,Pt)": {
		"languages": "Es,Pt"
	},
	"Reckless Racing (Brazil) (Es,Pt)": {
		"languages": "Es,Pt"
	},
	"Resident Evil 4 - Zeebo Edition (Brazil) (Es,Pt)": {
		"languages": "Es,Pt"
	},
	"Ridge Racer (Brazil) (Es,Pt)": {
		"languages": "Es,Pt"
	},
	"Spin Master (Brazil) (Es,Pt)": {
		"languages": "Es,Pt"
	},
	"Street Hoop (Brazil) (Es,Pt)": {
		"languages": "Es,Pt"
	},
	"Super BurgerTime (Brazil) (Es,Pt)": {
		"languages": "Es,Pt"
	},
	"Tekken 2 (Brazil) (Es,Pt)": {
		"languages": "Es,Pt"
	},
	"Tork and Kral - A Prehistorik Adventure (Brazil) (Es,Pt)": {
		"languages": "Es,Pt"
	},
	"Toy Raid (Brazil) (Es,Pt)": {
		"languages": "Es,Pt"
	},
	"Treino Cerebral (Brazil) (Es,Pt)": {
		"languages": "Es,Pt"
	},
	"Turma da Monica em Vamos Brincar Vol. 1 (Brazil) (Es,Pt)": {
		"languages": "Es,Pt"
	},
	"Ultimate Chess 3D (Brazil) (Es,Pt)": {
		"languages": "Es,Pt"
	},
	"Um Jogo de Ovos (Brazil) (Es,Pt)": {
		"languages": "Es,Pt"
	},
	"Wizard Fire (Brazil) (Es,Pt)": {
		"languages": "Es,Pt"
	},
	"Z-Wheel (Brazil) (Es,Pt)": {
		"languages": "Es,Pt"
	},
	"Zeebo App (Brazil) (Es,Pt)": {
		"languages": "Es,Pt"
	},
	"Zeebo Channels - Opera Mini (Brazil) (Es,Pt)": {
		"languages": "Es,Pt"
	},
	"Zeebo Clube (Brazil) (Es,Pt)": {
		"languages": "Es,Pt"
	},
	"Zeebo Extreme Baja (Brazil) (Es,Pt)": {
		"languages": "Es,Pt"
	},
	"Zeebo Extreme Boia Cross (Brazil) (Es,Pt)": {
		"languages": "Es,Pt"
	},
	"Zeebo Extreme Corrida Aerea (Brazil) (Es,Pt)": {
		"languages": "Es,Pt"
	},
	"Zeebo Extreme Jetboard (Brazil) (Es,Pt)": {
		"languages": "Es,Pt"
	},
	"Zeebo Extreme Rolima (Brazil) (Es,Pt)": {
		"languages": "Es,Pt"
	},
	"Zeebo F.C. Foot Camp (Brazil) (Es,Pt)": {
		"languages": "Es,Pt"
	},
	"Zeebo F.C. Super League (Brazil) (Es,Pt)": {
		"languages": "Es,Pt"
	},
	"Zeebo Family Pack (Brazil) (Es,Pt)": {
		"languages": "Es,Pt"
	},
	"Zeebo Sports Peteca (Brazil) (Es,Pt)": {
		"languages": "Es,Pt"
	},
	"Zeebo Sports Queimada (Brazil) (Es,Pt)": {
		"languages": "Es,Pt"
	},
	"Zeebo Sports Tenis (Brazil) (Es,Pt)": {
		"languages": "Es,Pt"
	},
	"Zeebo Sports Volei (Brazil) (Es,Pt)": {
		"languages": "Es,Pt"
	},
	"Zeeboids (Brazil) (Es,Pt)": {
		"languages": "Es,Pt"
	},
	"Zenonia (Brazil) (Es,Pt)": {
		"languages": "Es,Pt"
	},
	"Zuma's Revenge (Brazil) (Es,Pt)": {
		"languages": "Es,Pt"
	}
}